tap_sling
